netscape_cookies/__init__.py
netscape_cookies/netscape_cookies.py
netscape_cookies-1.0.0.dist-info/METADATA
netscape_cookies-1.0.0.dist-info/WHEEL
netscape_cookies-1.0.0.dist-info/top_level.txt
netscape_cookies-1.0.0.dist-info/RECORD
